nonebot_plugin_gachalogs/__init__.py
nonebot_plugin_gachalogs/__meta__.py
nonebot_plugin_gachalogs/data_export.py
nonebot_plugin_gachalogs/data_import.py
nonebot_plugin_gachalogs/data_render.py
nonebot_plugin_gachalogs/data_source.py
nonebot_plugin_gachalogs/gacha_achieve.py
nonebot_plugin_gachalogs-0.2.13.dist-info/LICENSE
nonebot_plugin_gachalogs-0.2.13.dist-info/METADATA
nonebot_plugin_gachalogs-0.2.13.dist-info/WHEEL
nonebot_plugin_gachalogs-0.2.13.dist-info/RECORD
