Metadata-Version: 2.1
Name: nonebot-plugin-gachalogs
Version: 0.2.13
Summary: Genshin gacha history analysis plugin for NoneBot2
Home-page: https://github.com/monsterxcn/nonebot-plugin-gachalogs
License: MIT
Keywords: nonebot,nonebot2,genshin,gacha
Author: monsterxcn
Author-email: monsterxcn@gmail.com
Requires-Python: >=3.8.1,<4.0
Classifier: License :: OSI Approved :: MIT License
Classifier: Programming Language :: Python :: 3
Classifier: Programming Language :: Python :: 3.9
Classifier: Programming Language :: Python :: 3.10
Classifier: Programming Language :: Python :: 3.11
Requires-Dist: httpx (>=0.20.0,<1.0.0)
Requires-Dist: matplotlib (>=3.5.1)
Requires-Dist: nonebot-adapter-onebot (>=2.0.0b1)
Requires-Dist: nonebot2 (>=2.0.0a16)
Requires-Dist: xlsxwriter (>=3.0.2)
Project-URL: Documentation, https://github.com/monsterxcn/nonebot-plugin-gachalogs#readme
